pdfdiagrams/Defaults.py
pdfdiagrams/Definitions.py
pdfdiagrams/Diagram.py
pdfdiagrams/DiagramCommon.py
pdfdiagrams/DiagramLine.py
pdfdiagrams/FPDFExtended.py
pdfdiagrams/Internal.py
pdfdiagrams/UnsupportedException.py
pdfdiagrams/__init__.py
pdfdiagrams/resources/__init__.py
tests/TestAll.py
tests/TestBase.py
tests/TestConstants.py
tests/TestDiagram.py
tests/TestDiagramCommon.py
tests/TestDiagramLine.py
tests/TestTemplate.py
tests/__init__.py
tests/simpleDemo.py
tests/resources/TestBase.py
tests/resources/__init__.py
PDFDiagramming-1.0.8.dist-info/METADATA
PDFDiagramming-1.0.8.dist-info/WHEEL
PDFDiagramming-1.0.8.dist-info/top_level.txt
PDFDiagramming-1.0.8.dist-info/RECORD
