Metadata-Version: 2.1
Name: PDFDiagramming
Version: 1.0.8
Summary: Draw UML diagrams in PDF format
Home-page: https://github.com/hasii2011/pdfdiagrams
License: UNKNOWN
Platform: UNKNOWN
Requires-Dist: fpdf2
